{
  "firmware": {
    "PD-KB401B": "A4.29",
    "PD-KB401B-EM": "A4.29",
    "PD-KB401B-PPM": "A4.29",
    "PD-KB401BN": "A4.29",
    "PD-KB401BN-EM": "A4.29",
    "PD-KB401BN-PPM": "A4.29",
    "PD-KB401W": "A4.29",
    "PD-KB401W-EM": "A4.29",
    "PD-KB401W-PPM": "A4.29",
    "PD-KB401WN": "A4.29",
    "PD-KB401WN-EM": "A4.29",
    "PD-KB401WN-PPM": "A4.29",
    "PD-KB800B": "A0.46",
    "PD-KB800B-EM": "A0.46",
    "PD-KB800B-PPM": "A0.46",
    "PD-KB800BN": "A0.46",
    "PD-KB800BN-EM": "A0.46",
    "PD-KB800BN-PPM": "A0.46",
    "PD-KB800BNS": "A0.46",
    "PD-KB800BNS-EM": "A0.46",
    "PD-KB800BNS-PPM": "A0.46",
    "PD-KB800BS": "A0.46",
    "PD-KB800BS-EM": "A0.46",
    "PD-KB800BS-PPM": "A0.46",
    "PD-KB800W": "A0.46",
    "PD-KB800W-EM": "A0.46",
    "PD-KB800W-PPM": "A0.46",
    "PD-KB800WN": "A0.46",
    "PD-KB800WN-EM": "A0.46",
    "PD-KB800WN-PPM": "A0.46",
    "PD-KB800WNS": "A0.46",
    "PD-KB800WNS-EM": "A0.46",
    "PD-KB800WNS-PPM": "A0.46",
    "PD-KB800WS": "A0.46",
    "PD-KB800WS-EM": "A0.46",
    "PD-KB800WS-PPM": "A0.46",
    "PD-KB800YNS": "A0.46",
    "PD-KB800YS": "A0.46",
    "PD-KB800YSC": "A0.46",
    "PD-KB820B": "A2.46",
    "PD-KB820B-EM": "A2.46",
    "PD-KB820B-PPM": "A2.46",
    "PD-KB820BS": "A2.46",
    "PD-KB820BS-EM": "A2.46",
    "PD-KB820BS-PPM": "A2.46",
    "PD-KB820W": "A2.46",
    "PD-KB820W-EM": "A2.46",
    "PD-KB820W-PPM": "A2.46",
    "PD-KB820WS": "A2.46",
    "PD-KB820WS-EM": "A2.46",
    "PD-KB820WS-PPM": "A2.46",
    "PD-KB820YNS": "A2.46",
    "PD-KB820YS": "A2.46",
    "PD-KB820YSC": "A2.46"
  },
  "keymapTool": {
    "Mac": "1.3.0.0",
    "Win": "1.3.0.1"
  }
}